[{"CustomerID":14911,"first_purchase_date":1259667660000,"last_purchase_date":1291897020000,"total_invoices":270,"total_items":66572,"total_spend":137710.76,"distinct_products":1749,"days_as_customer":374,"recency":1,"total_items_returned":3137.0,"total_value_returned":14410.46,"total_return_invoices":65.0,"return_rate_by_items":0.0450007173,"return_rate_by_value":0.0947294879,"return_rate_by_invoices":0.2398523985,"anomaly_score":-0.1940544634,"is_anomaly":-1},{"CustomerID":14156,"first_purchase_date":1259670600000,"last_purchase_date":1291376880000,"total_invoices":138,"total_items":106883,"total_spend":183163.55,"distinct_products":1094,"days_as_customer":374,"recency":7,"total_items_returned":1222.0,"total_value_returned":13386.19,"total_return_invoices":36.0,"return_rate_by_items":0.0113037204,"return_rate_by_value":0.0681055182,"return_rate_by_invoices":0.2589928058,"anomaly_score":-0.1747259336,"is_anomaly":-1},{"CustomerID":13694,"first_purchase_date":1259940360000,"last_purchase_date":1291205520000,"total_invoices":105,"total_items":123639,"total_spend":128172.42,"distinct_products":659,"days_as_customer":371,"recency":9,"total_items_returned":2254.0,"total_value_returned":3270.77,"total_return_invoices":11.0,"return_rate_by_items":0.0179039509,"return_rate_by_value":0.0248833364,"return_rate_by_invoices":0.1037735849,"anomaly_score":-0.1592703236,"is_anomaly":-1},{"CustomerID":15311,"first_purchase_date":1259666460000,"last_purchase_date":1291904100000,"total_invoices":158,"total_items":31975,"total_spend":54033.21,"distinct_products":601,"days_as_customer":374,"recency":1,"total_items_returned":809.0,"total_value_returned":1909.53,"total_return_invoices":37.0,"return_rate_by_items":0.0246759189,"return_rate_by_value":0.0341330415,"return_rate_by_invoices":0.2327044025,"anomaly_score":-0.1533489932,"is_anomaly":-1},{"CustomerID":14646,"first_purchase_date":1259772720000,"last_purchase_date":1291134480000,"total_invoices":87,"total_items":168437,"total_spend":243853.05,"distinct_products":607,"days_as_customer":373,"recency":10,"total_items_returned":1841.0,"total_value_returned":4543.45,"total_return_invoices":9.0,"return_rate_by_items":0.0108116679,"return_rate_by_value":0.0182910456,"return_rate_by_invoices":0.1022727273,"anomaly_score":-0.1515245419,"is_anomaly":-1},{"CustomerID":12931,"first_purchase_date":1259667960000,"last_purchase_date":1290593340000,"total_invoices":51,"total_items":24968,"total_spend":37836.86,"distinct_products":23,"days_as_customer":374,"recency":16,"total_items_returned":9934.0,"total_value_returned":12454.52,"total_return_invoices":9.0,"return_rate_by_items":0.2846173681,"return_rate_by_value":0.247642287,"return_rate_by_invoices":0.1730769231,"anomaly_score":-0.1501103452,"is_anomaly":-1},{"CustomerID":16754,"first_purchase_date":1268047920000,"last_purchase_date":1291311480000,"total_invoices":35,"total_items":54190,"total_spend":54558.18,"distinct_products":39,"days_as_customer":277,"recency":8,"total_items_returned":9361.0,"total_value_returned":10941.89,"total_return_invoices":6.0,"return_rate_by_items":0.1472967019,"return_rate_by_value":0.1670490268,"return_rate_by_invoices":0.1666666667,"anomaly_score":-0.1475546739,"is_anomaly":-1},{"CustomerID":17949,"first_purchase_date":1259752020000,"last_purchase_date":1291381920000,"total_invoices":87,"total_items":26757,"total_spend":46144.75,"distinct_products":35,"days_as_customer":373,"recency":7,"total_items_returned":3355.0,"total_value_returned":13972.85,"total_return_invoices":13.0,"return_rate_by_items":0.1114136752,"return_rate_by_value":0.2324214137,"return_rate_by_invoices":0.1477272727,"anomaly_score":-0.1470671715,"is_anomaly":-1},{"CustomerID":18102,"first_purchase_date":1259659440000,"last_purchase_date":1291902240000,"total_invoices":95,"total_items":122988,"total_spend":341776.73,"distinct_products":283,"days_as_customer":374,"recency":1,"total_items_returned":1228.0,"total_value_returned":7387.62,"total_return_invoices":6.0,"return_rate_by_items":0.0098859254,"return_rate_by_value":0.0211579414,"return_rate_by_invoices":0.0625,"anomaly_score":-0.1443770605,"is_anomaly":-1},{"CustomerID":13089,"first_purchase_date":1259768640000,"last_purchase_date":1291644000000,"total_invoices":132,"total_items":28417,"total_spend":55801.73,"distinct_products":476,"days_as_customer":373,"recency":4,"total_items_returned":708.0,"total_value_returned":2083.72,"total_return_invoices":23.0,"return_rate_by_items":0.0243081783,"return_rate_by_value":0.0359966797,"return_rate_by_invoices":0.1729323308,"anomaly_score":-0.1304138111,"is_anomaly":-1},{"CustomerID":16684,"first_purchase_date":1260190560000,"last_purchase_date":1290683040000,"total_invoices":34,"total_items":51705,"total_spend":75610.17,"distinct_products":125,"days_as_customer":368,"recency":15,"total_items_returned":2850.0,"total_value_returned":4879.04,"total_return_invoices":7.0,"return_rate_by_items":0.0522399003,"return_rate_by_value":0.0606165644,"return_rate_by_invoices":0.2,"anomaly_score":-0.1290049167,"is_anomaly":-1},{"CustomerID":12748,"first_purchase_date":1259947860000,"last_purchase_date":1291900920000,"total_invoices":159,"total_items":12621,"total_spend":20491.27,"distinct_products":1343,"days_as_customer":371,"recency":1,"total_items_returned":488.0,"total_value_returned":1966.63,"total_return_invoices":15.0,"return_rate_by_items":0.0372234935,"return_rate_by_value":0.0875657312,"return_rate_by_invoices":0.09375,"anomaly_score":-0.1282919676,"is_anomaly":-1},{"CustomerID":17841,"first_purchase_date":1259768460000,"last_purchase_date":1291915620000,"total_invoices":126,"total_items":14100,"total_spend":28844.93,"distinct_products":1514,"days_as_customer":373,"recency":1,"total_items_returned":232.0,"total_value_returned":717.09,"total_return_invoices":35.0,"return_rate_by_items":0.0161864229,"return_rate_by_value":0.0242563175,"return_rate_by_invoices":0.2755905512,"anomaly_score":-0.1274843033,"is_anomaly":-1},{"CustomerID":17399,"first_purchase_date":1276793520000,"last_purchase_date":1276793520000,"total_invoices":1,"total_items":-1,"total_spend":-25111.09,"distinct_products":1,"days_as_customer":176,"recency":176,"total_items_returned":1.0,"total_value_returned":25111.09,"total_return_invoices":1.0,"return_rate_by_items":1.0,"return_rate_by_value":25111.09,"return_rate_by_invoices":0.5,"anomaly_score":-0.1182648005,"is_anomaly":-1},{"CustomerID":17450,"first_purchase_date":1285606740000,"last_purchase_date":1291714980000,"total_invoices":8,"total_items":11967,"total_spend":46097.22,"distinct_products":80,"days_as_customer":74,"recency":3,"total_items_returned":2760.0,"total_value_returned":6325.08,"total_return_invoices":1.0,"return_rate_by_items":0.1873981532,"return_rate_by_value":0.120653984,"return_rate_by_invoices":0.1111111111,"anomaly_score":-0.1121605245,"is_anomaly":-1},{"CustomerID":14337,"first_purchase_date":1260281040000,"last_purchase_date":1260281040000,"total_invoices":1,"total_items":-393,"total_spend":-658.63,"distinct_products":36,"days_as_customer":367,"recency":367,"total_items_returned":393.0,"total_value_returned":658.63,"total_return_invoices":1.0,"return_rate_by_items":393.0,"return_rate_by_value":658.63,"return_rate_by_invoices":0.5,"anomaly_score":-0.1064502149,"is_anomaly":-1},{"CustomerID":16422,"first_purchase_date":1259675520000,"last_purchase_date":1291563300000,"total_invoices":72,"total_items":30396,"total_spend":27242.45,"distinct_products":99,"days_as_customer":374,"recency":5,"total_items_returned":2173.0,"total_value_returned":1662.22,"total_return_invoices":13.0,"return_rate_by_items":0.0667178385,"return_rate_by_value":0.0575049809,"return_rate_by_invoices":0.1780821918,"anomaly_score":-0.1062896991,"is_anomaly":-1},{"CustomerID":17013,"first_purchase_date":1271341320000,"last_purchase_date":1271343840000,"total_invoices":2,"total_items":-2,"total_spend":-3224.76,"distinct_products":1,"days_as_customer":239,"recency":239,"total_items_returned":2.0,"total_value_returned":3224.76,"total_return_invoices":2.0,"return_rate_by_items":2.0,"return_rate_by_value":3224.76,"return_rate_by_invoices":0.6666666667,"anomaly_score":-0.1053233376,"is_anomaly":-1},{"CustomerID":13091,"first_purchase_date":1260275100000,"last_purchase_date":1260449040000,"total_invoices":4,"total_items":-1535,"total_spend":-450.04,"distinct_products":38,"days_as_customer":367,"recency":365,"total_items_returned":2408.0,"total_value_returned":2426.04,"total_return_invoices":2.0,"return_rate_by_items":2.7551487414,"return_rate_by_value":1.2271320182,"return_rate_by_invoices":0.4,"anomaly_score":-0.1027491488,"is_anomaly":-1},{"CustomerID":13902,"first_purchase_date":1260292380000,"last_purchase_date":1268831340000,"total_invoices":8,"total_items":218090,"total_spend":30411.26,"distinct_products":60,"days_as_customer":367,"recency":268,"total_items_returned":2510.0,"total_value_returned":3684.0,"total_return_invoices":3.0,"return_rate_by_items":0.0113780083,"return_rate_by_value":0.1080470409,"return_rate_by_invoices":0.3333333333,"anomaly_score":-0.1021343315,"is_anomaly":-1}]